catch_sunset/.cli.py.~undo-tree~
catch_sunset/.config.py.~undo-tree~
catch_sunset/.ntfy_alarm.py.~undo-tree~
catch_sunset/__init__.py
catch_sunset/alerts.py
catch_sunset/astronomy.py
catch_sunset/cli.py
catch_sunset/cloudysky.py
catch_sunset/config.py
catch_sunset/gps.py
catch_sunset/moon.py
catch_sunset/ntfy_alarm.py
catch_sunset-0.1.6.dist-info/WHEEL
catch_sunset-0.1.6.dist-info/entry_points.txt
catch_sunset-0.1.6.dist-info/METADATA
catch_sunset-0.1.6.dist-info/RECORD
