Metadata-Version: 2.3
Name: catch-sunset
Version: 0.1.6
Summary: Add your description here
Author: ojr@core6a
Author-email: ojr@core6a <ojr@core6a>
Requires-Dist: astral>=3.2
Requires-Dist: click>=8.3.0
Requires-Dist: console>=0.9912
Requires-Dist: python-dateutil>=2.9.0.post0
Requires-Dist: requests
Requires-Dist: skyfield>=1.53
Requires-Python: >=3.11
